setup.py
multidex/__init__.py
multidex.egg-info/PKG-INFO
multidex.egg-info/SOURCES.txt
multidex.egg-info/dependency_links.txt
multidex.egg-info/pbr.json
multidex.egg-info/top_level.txt