Metadata-Version: 1.1
Name: multidex
Version: 0.1.1
Summary: MultiIndex dictionaries for fun and profit
Home-page: https://github.com/stuaxo/multidex
Author: Stuart Axon
Author-email: stuaxo2@yahoo.com
License: MIT
Keywords: dict lookup index
Platform: UNKNOWN
Classifier: Development Status :: 3 - Alpha
Classifier: Intended Audience :: Developers
Classifier: Topic :: Software Development :: Build Tools
Classifier: License :: OSI Approved :: MIT License
Classifier: Programming Language :: Python :: 2.7
Classifier: Programming Language :: Python :: 3.4
